koeda/__init__.py
koeda/aeda.py
koeda/eda.py
koeda/augmenters/__init__.py
koeda/augmenters/deletion.py
koeda/augmenters/insertion.py
koeda/augmenters/replacement.py
koeda/augmenters/swap.py
koeda/corpora/stopwords.json
koeda/corpora/wordnet.json
koeda/utils/__init__.py
koeda/utils/space.py
koeda/utils/stopwords.py
koeda/utils/synonyms.py
koeda/utils/wordnet.py
koeda-0.0.4.dist-info/LICENSE
koeda-0.0.4.dist-info/METADATA
koeda-0.0.4.dist-info/WHEEL
koeda-0.0.4.dist-info/top_level.txt
koeda-0.0.4.dist-info/RECORD
