Metadata-Version: 2.1
Name: koeda
Version: 0.0.4
Summary: Korean Easy Data Augmentation Package
Home-page: https://github.com/toriving/KoEDA
Author: Dongju.Park
Author-email: toriving@gmail.com
License: MIT
Keywords: NLP deep learning koeda korean easy data augmentation
Platform: UNKNOWN
Classifier: Development Status :: 5 - Production/Stable
Classifier: Intended Audience :: Developers
Classifier: Intended Audience :: Education
Classifier: Intended Audience :: Science/Research
Classifier: License :: OSI Approved :: MIT License
Classifier: Operating System :: OS Independent
Classifier: Programming Language :: Python :: 3
Classifier: Programming Language :: Python :: 3.7
Classifier: Programming Language :: Python :: 3.8
Classifier: Programming Language :: Python :: 3.9
Classifier: Topic :: Scientific/Engineering :: Artificial Intelligence
Requires-Python: >=3.7.0
License-File: LICENSE
Requires-Dist: numpy (>=1.19.4)
Requires-Dist: konlpy (>=0.5.2)
Requires-Dist: tweepy (==3.10.0)
